browshot.py
tests/__init__.py
tests/browshot_test.py
Browshot-1.21.1.dist-info/METADATA
Browshot-1.21.1.dist-info/WHEEL
Browshot-1.21.1.dist-info/top_level.txt
Browshot-1.21.1.dist-info/RECORD
