Metadata-Version: 2.1
Name: Browshot
Version: 1.21.1
Summary: Client to interact with Browshot
Home-page: https://github.com/juliensobrier/browshot-python
Author: Julien Sobrier
Author-email: julien@sobrier.net
License: Apache
Platform: UNKNOWN
Classifier: Development Status :: 4 - Beta
Classifier: Environment :: Console
Classifier: Intended Audience :: Developers
Classifier: Intended Audience :: Information Technology
Classifier: License :: OSI Approved :: BSD License
Classifier: Operating System :: OS Independent
Classifier: Programming Language :: Python
Requires-Dist: simplejson
Requires-Dist: requests
